README.md
setup.py
graphlearn/__init__.py
graphlearn/_version.py
graphlearn/choice.py
graphlearn/cipcorevector.py
graphlearn/local_substitution_graph_grammar.py
graphlearn/lsgg_core_interface_pair.py
graphlearn/lsgg_ego.py
graphlearn/lsgg_layered.py
graphlearn/lsgg_pisi.py
graphlearn/lsgg_pisilayer.py
graphlearn/sample.py
graphlearn/score.py
graphlearn/structurepreserve.py
graphlearn.egg-info/PKG-INFO
graphlearn.egg-info/SOURCES.txt
graphlearn.egg-info/dependency_links.txt
graphlearn.egg-info/requires.txt
graphlearn.egg-info/top_level.txt
graphlearn/test/__init__.py
graphlearn/test/cycler.py
graphlearn/test/test_lsgg.py
graphlearn/test/test_lsgg_corvec.py
graphlearn/test/test_lsgg_ego.py
graphlearn/test/test_lsgg_stupe.py
graphlearn/test/test_pisi.py
graphlearn/test/transformutil.py
graphlearn/util/__init__.py
graphlearn/util/multi.py
graphlearn/util/setoperations.py
graphlearn/util/util.py