Metadata-Version: 1.0
Name: graphlearn
Version: 0.0.932
Summary: recombine network graphs
Home-page: https://github.com/fabriziocosta/GraphLearn
Author: Stefan Mautner
Author-email: myl4stn4m3@cs.uni-freiburg.de
License: LICENSE
Platform: UNKNOWN
